NucleusUtils/__init__.py
NucleusUtils/chest/__init__.py
NucleusUtils/chest/container.py
NucleusUtils/chest/context.py
NucleusUtils/chest/exceptions.py
NucleusUtils/config/__init__.py
NucleusUtils/config/engines/__init__.py
NucleusUtils/config/engines/base.py
NucleusUtils/config/engines/json.py
NucleusUtils/config/engines/xml.py
NucleusUtils/events/__init__.py
NucleusUtils/events/attr.py
NucleusUtils/events/lock.py
NucleusUtils/files/__init__.py
NucleusUtils/files/watcher.py
NucleusUtils/jProtocol/__init__.py
NucleusUtils/jProtocol/client.py
NucleusUtils/jProtocol/entity.py
NucleusUtils/jProtocol/exceptions.py
NucleusUtils/jProtocol/helper.py
NucleusUtils/jProtocol/objects.py
NucleusUtils/jProtocol/router.py
NucleusUtils/logging/__init__.py
NucleusUtils/logging/decorators.py
NucleusUtils/logging/dumps.py
NucleusUtils/py/__init__.py
NucleusUtils/queues/__init__.py
NucleusUtils/queues/iterator.py
NucleusUtils/signals/__init__.py
NucleusUtils/signals/sig.py
NucleusUtils/simple/__init__.py
NucleusUtils/simple/dict.py
NucleusUtils/singleton/__init__.py
NucleusUtils/stack/__init__.py
NucleusUtils/stack/link.py
NucleusUtils/stack/memory.py
NucleusUtils/stack/stack.py
NucleusUtils/threads/__init__.py
NucleusUtils/translations/__init__.py
NucleusUtils/translations/advanced.py
NucleusUtils/translations/converter.py
NucleusUtils/translations/filters.py
NucleusUtils/translations/singleton.py
NucleusUtils/translations/text_utils.py
NucleusUtils/trash/__init__.py
NucleusUtils/trash/context.py
NucleusUtils/versions/__init__.py
NucleusUtils/versions/deprecated.py
NucleusUtils/web/__init__.py
NucleusUtils/web/html.py
NucleusUtils-0.1.11b1.dist-info/DESCRIPTION.rst
NucleusUtils-0.1.11b1.dist-info/METADATA
NucleusUtils-0.1.11b1.dist-info/RECORD
NucleusUtils-0.1.11b1.dist-info/WHEEL
NucleusUtils-0.1.11b1.dist-info/metadata.json
NucleusUtils-0.1.11b1.dist-info/top_level.txt
