Metadata-Version: 2.0
Name: NucleusUtils
Version: 0.1.11b1
Summary: Collection of Nucleus utils
Home-page: https://bitbucket.org/illemius/nucleusutils
Author: Illemius/Alex Root Junior
Author-email: jroot.junio@gmail.com
License: MIT
Keywords: Illemius,NucleusUtils,Utilities
Platform: UNKNOWN
Classifier: Development Status :: 4 - Beta
Classifier: Intended Audience :: Developers
Classifier: Intended Audience :: Education
Classifier: Intended Audience :: End Users/Desktop
Classifier: Intended Audience :: System Administrators
Classifier: License :: OSI Approved :: MIT License
Classifier: Programming Language :: Python
Classifier: Programming Language :: Python :: 3.6
Classifier: Topic :: Software Development :: Libraries :: Python Modules
Classifier: Topic :: Utilities
Requires-Dist: jinja2
